simple_web_discover/__init__.py
simple_web_discover/main.py
simple_web_discover/web.py
simple_web_discover-1.0.0.dist-info/METADATA
simple_web_discover-1.0.0.dist-info/RECORD
simple_web_discover-1.0.0.dist-info/WHEEL
simple_web_discover-1.0.0.dist-info/entry_points.txt
simple_web_discover-1.0.0.dist-info/top_level.txt
